hatch_test/__about__.py
hatch_test/__init__.py
hatch_test/__main__.py
hatch_test/utils/__init__.py
hatch_test/utils/test_util.py
hatch_test-0.1.5.dist-info/METADATA
hatch_test-0.1.5.dist-info/WHEEL
hatch_test-0.1.5.dist-info/entry_points.txt
hatch_test-0.1.5.dist-info/licenses/LICENSE.txt
hatch_test-0.1.5.dist-info/RECORD
