Metadata-Version: 2.4
Name: hatch-test
Version: 0.1.5
Project-URL: Documentation, https://github.com/Kaburi/hatch-test#readme
Project-URL: Issues, https://github.com/Kaburi/hatch-test/issues
Project-URL: Source, https://github.com/Kaburi/hatch-test
Author-email: Kaburi <specialemail90@gmail.com>
License-Expression: MIT
License-File: LICENSE.txt
Classifier: Development Status :: 4 - Beta
Classifier: Programming Language :: Python
Classifier: Programming Language :: Python :: 3.8
Classifier: Programming Language :: Python :: 3.9
Classifier: Programming Language :: Python :: 3.10
Classifier: Programming Language :: Python :: 3.11
Classifier: Programming Language :: Python :: 3.12
Classifier: Programming Language :: Python :: 3.13
Classifier: Programming Language :: Python :: Implementation :: CPython
Classifier: Programming Language :: Python :: Implementation :: PyPy
Requires-Python: >=3.13
Requires-Dist: mcp[cli]>=1.6.0
